{
  "id": "8630e4c2-b38d-4091-a5b7-3f82b5c2d7da",
  "prevId": "00000000-0000-0000-0000-000000000000",
  "version": "7",
  "dialect": "postgresql",
  "tables": {
    "public.assets": {
      "name": "assets",
      "schema": "",
      "columns": {
        "id": {
          "name": "id",
          "type": "uuid",
          "primaryKey": true,
          "notNull": true,
          "default": "gen_random_uuid()"
        },
        "job_id": {
          "name": "job_id",
          "type": "uuid",
          "primaryKey": false,
          "notNull": true
        },
        "file_name": {
          "name": "file_name",
          "type": "text",
          "primaryKey": false,
          "notNull": true
        },
        "file_type": {
          "name": "file_type",
          "type": "text",
          "primaryKey": false,
          "notNull": false
        },
        "file_url": {
          "name": "file_url",
          "type": "text",
          "primaryKey": false,
          "notNull": true
        },
        "created_at": {
          "name": "created_at",
          "type": "timestamp",
          "primaryKey": false,
          "notNull": true,
          "default": "now()"
        }
      },
      "indexes": {},
      "foreignKeys": {
        "assets_job_id_intake_jobs_id_fk": {
          "name": "assets_job_id_intake_jobs_id_fk",
          "tableFrom": "assets",
          "tableTo": "intake_jobs",
          "columnsFrom": [
            "job_id"
          ],
          "columnsTo": [
            "id"
          ],
          "onDelete": "no action",
          "onUpdate": "no action"
        }
      },
      "compositePrimaryKeys": {},
      "uniqueConstraints": {},
      "policies": {},
      "checkConstraints": {},
      "isRLSEnabled": false
    },
    "public.cost_logs": {
      "name": "cost_logs",
      "schema": "",
      "columns": {
        "id": {
          "name": "id",
          "type": "uuid",
          "primaryKey": true,
          "notNull": true,
          "default": "gen_random_uuid()"
        },
        "job_id": {
          "name": "job_id",
          "type": "uuid",
          "primaryKey": false,
          "notNull": true
        },
        "stage": {
          "name": "stage",
          "type": "text",
          "primaryKey": false,
          "notNull": true
        },
        "model": {
          "name": "model",
          "type": "text",
          "primaryKey": false,
          "notNull": false
        },
        "input_tokens": {
          "name": "input_tokens",
          "type": "integer",
          "primaryKey": false,
          "notNull": false,
          "default": 0
        },
        "output_tokens": {
          "name": "output_tokens",
          "type": "integer",
          "primaryKey": false,
          "notNull": false,
          "default": 0
        },
        "estimated_cost": {
          "name": "estimated_cost",
          "type": "numeric",
          "primaryKey": false,
          "notNull": false
        },
        "created_at": {
          "name": "created_at",
          "type": "timestamp",
          "primaryKey": false,
          "notNull": true,
          "default": "now()"
        }
      },
      "indexes": {},
      "foreignKeys": {
        "cost_logs_job_id_intake_jobs_id_fk": {
          "name": "cost_logs_job_id_intake_jobs_id_fk",
          "tableFrom": "cost_logs",
          "tableTo": "intake_jobs",
          "columnsFrom": [
            "job_id"
          ],
          "columnsTo": [
            "id"
          ],
          "onDelete": "no action",
          "onUpdate": "no action"
        }
      },
      "compositePrimaryKeys": {},
      "uniqueConstraints": {},
      "policies": {},
      "checkConstraints": {},
      "isRLSEnabled": false
    },
    "public.deployments": {
      "name": "deployments",
      "schema": "",
      "columns": {
        "id": {
          "name": "id",
          "type": "uuid",
          "primaryKey": true,
          "notNull": true,
          "default": "gen_random_uuid()"
        },
        "job_id": {
          "name": "job_id",
          "type": "uuid",
          "primaryKey": false,
          "notNull": true
        },
        "live_url": {
          "name": "live_url",
          "type": "text",
          "primaryKey": false,
          "notNull": true
        },
        "deployed_at": {
          "name": "deployed_at",
          "type": "timestamp",
          "primaryKey": false,
          "notNull": false,
          "default": "now()"
        },
        "deployed_by": {
          "name": "deployed_by",
          "type": "uuid",
          "primaryKey": false,
          "notNull": false
        },
        "total_cost": {
          "name": "total_cost",
          "type": "numeric",
          "primaryKey": false,
          "notNull": false
        }
      },
      "indexes": {},
      "foreignKeys": {
        "deployments_job_id_intake_jobs_id_fk": {
          "name": "deployments_job_id_intake_jobs_id_fk",
          "tableFrom": "deployments",
          "tableTo": "intake_jobs",
          "columnsFrom": [
            "job_id"
          ],
          "columnsTo": [
            "id"
          ],
          "onDelete": "no action",
          "onUpdate": "no action"
        },
        "deployments_deployed_by_users_id_fk": {
          "name": "deployments_deployed_by_users_id_fk",
          "tableFrom": "deployments",
          "tableTo": "users",
          "columnsFrom": [
            "deployed_by"
          ],
          "columnsTo": [
            "id"
          ],
          "onDelete": "no action",
          "onUpdate": "no action"
        }
      },
      "compositePrimaryKeys": {},
      "uniqueConstraints": {
        "deployments_job_id_unique": {
          "name": "deployments_job_id_unique",
          "nullsNotDistinct": false,
          "columns": [
            "job_id"
          ]
        }
      },
      "policies": {},
      "checkConstraints": {},
      "isRLSEnabled": false
    },
    "public.intake_jobs": {
      "name": "intake_jobs",
      "schema": "",
      "columns": {
        "id": {
          "name": "id",
          "type": "uuid",
          "primaryKey": true,
          "notNull": true,
          "default": "gen_random_uuid()"
        },
        "org_id": {
          "name": "org_id",
          "type": "uuid",
          "primaryKey": false,
          "notNull": true
        },
        "status": {
          "name": "status",
          "type": "intake_job_status",
          "typeSchema": "public",
          "primaryKey": false,
          "notNull": false,
          "default": "'queued'"
        },
        "current_stage": {
          "name": "current_stage",
          "type": "text",
          "primaryKey": false,
          "notNull": false
        },
        "preview_url": {
          "name": "preview_url",
          "type": "text",
          "primaryKey": false,
          "notNull": false
        },
        "live_url": {
          "name": "live_url",
          "type": "text",
          "primaryKey": false,
          "notNull": false
        },
        "created_at": {
          "name": "created_at",
          "type": "timestamp",
          "primaryKey": false,
          "notNull": true,
          "default": "now()"
        },
        "updated_at": {
          "name": "updated_at",
          "type": "timestamp",
          "primaryKey": false,
          "notNull": true,
          "default": "now()"
        }
      },
      "indexes": {},
      "foreignKeys": {
        "intake_jobs_org_id_organizations_id_fk": {
          "name": "intake_jobs_org_id_organizations_id_fk",
          "tableFrom": "intake_jobs",
          "tableTo": "organizations",
          "columnsFrom": [
            "org_id"
          ],
          "columnsTo": [
            "id"
          ],
          "onDelete": "no action",
          "onUpdate": "no action"
        }
      },
      "compositePrimaryKeys": {},
      "uniqueConstraints": {},
      "policies": {},
      "checkConstraints": {},
      "isRLSEnabled": false
    },
    "public.job_stages": {
      "name": "job_stages",
      "schema": "",
      "columns": {
        "id": {
          "name": "id",
          "type": "uuid",
          "primaryKey": true,
          "notNull": true,
          "default": "gen_random_uuid()"
        },
        "job_id": {
          "name": "job_id",
          "type": "uuid",
          "primaryKey": false,
          "notNull": true
        },
        "stage": {
          "name": "stage",
          "type": "text",
          "primaryKey": false,
          "notNull": true
        },
        "status": {
          "name": "status",
          "type": "job_stage_status",
          "typeSchema": "public",
          "primaryKey": false,
          "notNull": false
        },
        "started_at": {
          "name": "started_at",
          "type": "timestamp",
          "primaryKey": false,
          "notNull": false
        },
        "completed_at": {
          "name": "completed_at",
          "type": "timestamp",
          "primaryKey": false,
          "notNull": false
        },
        "error_message": {
          "name": "error_message",
          "type": "text",
          "primaryKey": false,
          "notNull": false
        }
      },
      "indexes": {},
      "foreignKeys": {
        "job_stages_job_id_intake_jobs_id_fk": {
          "name": "job_stages_job_id_intake_jobs_id_fk",
          "tableFrom": "job_stages",
          "tableTo": "intake_jobs",
          "columnsFrom": [
            "job_id"
          ],
          "columnsTo": [
            "id"
          ],
          "onDelete": "no action",
          "onUpdate": "no action"
        }
      },
      "compositePrimaryKeys": {},
      "uniqueConstraints": {},
      "policies": {},
      "checkConstraints": {},
      "isRLSEnabled": false
    },
    "public.organizations": {
      "name": "organizations",
      "schema": "",
      "columns": {
        "id": {
          "name": "id",
          "type": "uuid",
          "primaryKey": true,
          "notNull": true,
          "default": "gen_random_uuid()"
        },
        "name": {
          "name": "name",
          "type": "text",
          "primaryKey": false,
          "notNull": true
        },
        "mission": {
          "name": "mission",
          "type": "text",
          "primaryKey": false,
          "notNull": false
        },
        "contact_email": {
          "name": "contact_email",
          "type": "text",
          "primaryKey": false,
          "notNull": false
        },
        "contact_name": {
          "name": "contact_name",
          "type": "text",
          "primaryKey": false,
          "notNull": false
        },
        "cause_area": {
          "name": "cause_area",
          "type": "text",
          "primaryKey": false,
          "notNull": false
        },
        "status": {
          "name": "status",
          "type": "organization_status",
          "typeSchema": "public",
          "primaryKey": false,
          "notNull": false,
          "default": "'prospect'"
        },
        "created_at": {
          "name": "created_at",
          "type": "timestamp",
          "primaryKey": false,
          "notNull": true,
          "default": "now()"
        },
        "updated_at": {
          "name": "updated_at",
          "type": "timestamp",
          "primaryKey": false,
          "notNull": true,
          "default": "now()"
        }
      },
      "indexes": {},
      "foreignKeys": {},
      "compositePrimaryKeys": {},
      "uniqueConstraints": {},
      "policies": {},
      "checkConstraints": {},
      "isRLSEnabled": false
    },
    "public.reviewer_actions": {
      "name": "reviewer_actions",
      "schema": "",
      "columns": {
        "id": {
          "name": "id",
          "type": "uuid",
          "primaryKey": true,
          "notNull": true,
          "default": "gen_random_uuid()"
        },
        "job_id": {
          "name": "job_id",
          "type": "uuid",
          "primaryKey": false,
          "notNull": true
        },
        "reviewer_id": {
          "name": "reviewer_id",
          "type": "uuid",
          "primaryKey": false,
          "notNull": true
        },
        "action": {
          "name": "action",
          "type": "reviewer_action",
          "typeSchema": "public",
          "primaryKey": false,
          "notNull": true
        },
        "feedback": {
          "name": "feedback",
          "type": "text",
          "primaryKey": false,
          "notNull": false
        },
        "created_at": {
          "name": "created_at",
          "type": "timestamp",
          "primaryKey": false,
          "notNull": true,
          "default": "now()"
        }
      },
      "indexes": {},
      "foreignKeys": {
        "reviewer_actions_job_id_intake_jobs_id_fk": {
          "name": "reviewer_actions_job_id_intake_jobs_id_fk",
          "tableFrom": "reviewer_actions",
          "tableTo": "intake_jobs",
          "columnsFrom": [
            "job_id"
          ],
          "columnsTo": [
            "id"
          ],
          "onDelete": "no action",
          "onUpdate": "no action"
        },
        "reviewer_actions_reviewer_id_users_id_fk": {
          "name": "reviewer_actions_reviewer_id_users_id_fk",
          "tableFrom": "reviewer_actions",
          "tableTo": "users",
          "columnsFrom": [
            "reviewer_id"
          ],
          "columnsTo": [
            "id"
          ],
          "onDelete": "no action",
          "onUpdate": "no action"
        }
      },
      "compositePrimaryKeys": {},
      "uniqueConstraints": {},
      "policies": {},
      "checkConstraints": {},
      "isRLSEnabled": false
    },
    "public.users": {
      "name": "users",
      "schema": "",
      "columns": {
        "id": {
          "name": "id",
          "type": "uuid",
          "primaryKey": true,
          "notNull": true,
          "default": "gen_random_uuid()"
        },
        "email": {
          "name": "email",
          "type": "text",
          "primaryKey": false,
          "notNull": true
        },
        "name": {
          "name": "name",
          "type": "text",
          "primaryKey": false,
          "notNull": false
        },
        "role": {
          "name": "role",
          "type": "user_role",
          "typeSchema": "public",
          "primaryKey": false,
          "notNull": false,
          "default": "'member'"
        },
        "email_verified": {
          "name": "email_verified",
          "type": "timestamp",
          "primaryKey": false,
          "notNull": false
        },
        "image": {
          "name": "image",
          "type": "text",
          "primaryKey": false,
          "notNull": false
        },
        "created_at": {
          "name": "created_at",
          "type": "timestamp",
          "primaryKey": false,
          "notNull": true,
          "default": "now()"
        },
        "updated_at": {
          "name": "updated_at",
          "type": "timestamp",
          "primaryKey": false,
          "notNull": true,
          "default": "now()"
        }
      },
      "indexes": {},
      "foreignKeys": {},
      "compositePrimaryKeys": {},
      "uniqueConstraints": {
        "users_email_unique": {
          "name": "users_email_unique",
          "nullsNotDistinct": false,
          "columns": [
            "email"
          ]
        }
      },
      "policies": {},
      "checkConstraints": {},
      "isRLSEnabled": false
    }
  },
  "enums": {
    "public.intake_job_status": {
      "name": "intake_job_status",
      "schema": "public",
      "values": [
        "queued",
        "in_progress",
        "awaiting_review",
        "approved",
        "deployed",
        "failed"
      ]
    },
    "public.job_stage_status": {
      "name": "job_stage_status",
      "schema": "public",
      "values": [
        "pending",
        "running",
        "completed",
        "failed"
      ]
    },
    "public.organization_status": {
      "name": "organization_status",
      "schema": "public",
      "values": [
        "prospect",
        "applicant",
        "active",
        "alumni"
      ]
    },
    "public.reviewer_action": {
      "name": "reviewer_action",
      "schema": "public",
      "values": [
        "approved",
        "rejected"
      ]
    },
    "public.user_role": {
      "name": "user_role",
      "schema": "public",
      "values": [
        "admin",
        "reviewer",
        "member"
      ]
    }
  },
  "schemas": {},
  "sequences": {},
  "roles": {},
  "policies": {},
  "views": {},
  "_meta": {
    "columns": {},
    "schemas": {},
    "tables": {}
  }
}